algorecell_types/__init__.py
algorecell_types-1.0.dist-info/METADATA
algorecell_types-1.0.dist-info/WHEEL
algorecell_types-1.0.dist-info/top_level.txt
algorecell_types-1.0.dist-info/RECORD
