Metadata-Version: 2.1
Name: algorecell-types
Version: 1.0
Summary: Generic types for reprogramming predictions from logical models
Home-page: https://github.com/algorecell/algorecell_types
Author: Loïc Paulevé
Author-email: loic.pauleve@labri.fr
License: UNKNOWN
Platform: UNKNOWN
Classifier: Intended Audience :: Science/Research
Classifier: Topic :: Scientific/Engineering :: Bio-Informatics
Requires-Dist: colomoto-jupyter
Requires-Dist: pandas
Requires-Dist: pydot
